Workbook

Sheet Budget Summary
A1: Crashfree India — Annual Operating Plan 2026-27
A2: Budget Summary | July 2026 - June 2027 | Total: Rs 6.00 Cr
A4: Vertical | B4: Q1 (Jul-Sep) | C4: Q2 (Oct-Dec) | D4: Q3 (Jan-Mar) | E4: Q4 (Apr-Jun) | F4: Total (Rs Lakh) | G4: Total (Rs Cr) | H4: % of Total
A5: Project Rakshak | B5: =SUMIF('Budget Detail'!$A$5:$A$44,$A5,'Budget Detail'!E$5:E$44) -> 37.75 | C5: =SUMIF('Budget Detail'!$A$5:$A$44,$A5,'Budget Detail'!F$5:F$44) -> 54.75 | D5: =SUMIF('Budget Detail'!$A$5:$A$44,$A5,'Budget Detail'!G$5:G$44) -> 51.25 | E5: =SUMIF('Budget Detail'!$A$5:$A$44,$A5,'Budget Detail'!H$5:H$44) -> 41.25 | F5: =SUM(B5:E5) -> 185 | G5: =F5/100 -> 1.85 | H5: =F5/$F$12 -> 0.30833333
A6: Civic & GovTech (SATARK) | B6: =SUMIF('Budget Detail'!$A$5:$A$44,$A6,'Budget Detail'!E$5:E$44) -> 21 | C6: =SUMIF('Budget Detail'!$A$5:$A$44,$A6,'Budget Detail'!F$5:F$44) -> 26 | D6: =SUMIF('Budget Detail'!$A$5:$A$44,$A6,'Budget Detail'!G$5:G$44) -> 26.5 | E6: =SUMIF('Budget Detail'!$A$5:$A$44,$A6,'Budget Detail'!H$5:H$44) -> 26.5 | F6: =SUM(B6:E6) -> 100 | G6: =F6/100 -> 1 | H6: =F6/$F$12 -> 0.16666667
A7: Hit & Run Compensation | B7: =SUMIF('Budget Detail'!$A$5:$A$44,$A7,'Budget Detail'!E$5:E$44) -> 15.5 | C7: =SUMIF('Budget Detail'!$A$5:$A$44,$A7,'Budget Detail'!F$5:F$44) -> 16 | D7: =SUMIF('Budget Detail'!$A$5:$A$44,$A7,'Budget Detail'!G$5:G$44) -> 14 | E7: =SUMIF('Budget Detail'!$A$5:$A$44,$A7,'Budget Detail'!H$5:H$44) -> 14.5 | F7: =SUM(B7:E7) -> 60 | G7: =F7/100 -> 0.6 | H7: =F7/$F$12 -> 0.1
A8: Marketing Campaign | B8: =SUMIF('Budget Detail'!$A$5:$A$44,$A8,'Budget Detail'!E$5:E$44) -> 6 | C8: =SUMIF('Budget Detail'!$A$5:$A$44,$A8,'Budget Detail'!F$5:F$44) -> 16 | D8: =SUMIF('Budget Detail'!$A$5:$A$44,$A8,'Budget Detail'!G$5:G$44) -> 21 | E8: =SUMIF('Budget Detail'!$A$5:$A$44,$A8,'Budget Detail'!H$5:H$44) -> 17 | F8: =SUM(B8:E8) -> 60 | G8: =F8/100 -> 0.6 | H8: =F8/$F$12 -> 0.1
A9: Trust Admin | B9: =SUMIF('Budget Detail'!$A$5:$A$44,$A9,'Budget Detail'!E$5:E$44) -> 36.25 | C9: =SUMIF('Budget Detail'!$A$5:$A$44,$A9,'Budget Detail'!F$5:F$44) -> 38.25 | D9: =SUMIF('Budget Detail'!$A$5:$A$44,$A9,'Budget Detail'!G$5:G$44) -> 37.75 | E9: =SUMIF('Budget Detail'!$A$5:$A$44,$A9,'Budget Detail'!H$5:H$44) -> 38.75 | F9: =SUM(B9:E9) -> 151 | G9: =F9/100 -> 1.51 | H9: =F9/$F$12 -> 0.25166667
A10: Bets (Seed Fund) | B10: =SUMIF('Budget Detail'!$A$5:$A$44,$A10,'Budget Detail'!E$5:E$44) -> 0 | C10: =SUMIF('Budget Detail'!$A$5:$A$44,$A10,'Budget Detail'!F$5:F$44) -> 4 | D10: =SUMIF('Budget Detail'!$A$5:$A$44,$A10,'Budget Detail'!G$5:G$44) -> 8 | E10: =SUMIF('Budget Detail'!$A$5:$A$44,$A10,'Budget Detail'!H$5:H$44) -> 8 | F10: =SUM(B10:E10) -> 20 | G10: =F10/100 -> 0.2 | H10: =F10/$F$12 -> 0.033333333
A11: Contingency | B11: =SUMIF('Budget Detail'!$A$5:$A$44,$A11,'Budget Detail'!E$5:E$44) -> 6 | C11: =SUMIF('Budget Detail'!$A$5:$A$44,$A11,'Budget Detail'!F$5:F$44) -> 6 | D11: =SUMIF('Budget Detail'!$A$5:$A$44,$A11,'Budget Detail'!G$5:G$44) -> 6 | E11: =SUMIF('Budget Detail'!$A$5:$A$44,$A11,'Budget Detail'!H$5:H$44) -> 6 | F11: =SUM(B11:E11) -> 24 | G11: =F11/100 -> 0.24 | H11: =F11/$F$12 -> 0.04
A12: TOTAL | B12: =SUM(B5:B11) -> 122.5 | C12: =SUM(C5:C11) -> 161 | D12: =SUM(D5:D11) -> 164.5 | E12: =SUM(E5:E11) -> 152 | F12: =SUM(F5:F11) -> 600 | G12: =SUM(G5:G11) -> 6 | H12: =SUM(H5:H11) -> 1
A14: Programme spend (Rakshak + Civic & GovTech + H&R + Marketing + Bets seed): Rs 4.25 Cr (~71%) | Trust Admin: Rs 1.51 Cr (~25%) | Contingency: Rs 0.24 Cr (4%)

Sheet Budget Detail
A1: Crashfree India — AOP 2026-27 Budget Detail
A2: All quarterly figures in Rs Lakh. Blue cells are editable inputs; totals recalculate automatically. Period: July 2026 - June 2027.
A4: Vertical | B4: Programme / Activity | C4: Line Item | D4: Basis of Estimate | E4: Q1 (Jul-Sep) | F4: Q2 (Oct-Dec) | G4: Q3 (Jan-Mar) | H4: Q4 (Apr-Jun) | I4: Total (Rs Lakh) | J4: Total (Rs)
A5: Project Rakshak | B5: Cohort 2 — Audit Pipeline | C5: Student team stipends | D5: 100 teams x Rs 36,000 (4-month cohort; performance-linked tranches) | E5: 9 | F5: 18 | G5: 9 | H5: 0 | I5: =SUM(E5:H5) -> 36 | J5: =I5*100000 -> 3600000
A6: Project Rakshak | B6: Cohort 2 — Audit Pipeline | C6: Mentor honorarium | D6: 25 faculty/expert mentors x Rs 24,000 | E6: 1.5 | F6: 2.5 | G6: 2 | H6: 0 | I6: =SUM(E6:H6) -> 6 | J6: =I6*100000 -> 600000
A7: Project Rakshak | B7: Cohort 2 — Audit Pipeline | C7: Certified RSA audits (Track C) | D7: ~40 NH/complex-junction sites x Rs 25,000 (CRRI-certified RSAs, IRC SP:88) | E7: 3 | F7: 4 | G7: 3 | H7: 0 | I7: =SUM(E7:H7) -> 10 | J7: =I7*100000 -> 1000000
A8: Project Rakshak | B8: Cohort 2 — Audit Pipeline | C8: NGO partner grants (Track B) | D8: ~20 district/peri-urban sites; incl. 10-15% physical re-checks by CFI | E8: 3 | F8: 5 | G8: 4 | H8: 0 | I8: =SUM(E8:H8) -> 12 | J8: =I8*100000 -> 1200000
A9: Project Rakshak | B9: Programme Management | C9: Programme team (fellows, PM, advocacy) | D9: 2-3 fellows + programme staff stipends, 12 months | E9: 8 | F9: 9 | G9: 8 | H9: 8 | I9: =SUM(E9:H9) -> 33 | J9: =I9*100000 -> 3300000
A10: Project Rakshak | B10: Institutionalisation | C10: Expert Consortium + Rakshak Audit Manual v1.0 | D10: 4 consortium meetings/yr + manual drafting, design & print | E10: 2 | F10: 1 | G10: 2 | H10: 1 | I10: =SUM(E10:H10) -> 6 | J10: =I10*100000 -> 600000
A11: Project Rakshak | B11: Institutionalisation | C11: Public dashboard & tech maintenance | D11: Hosting, dev upkeep of accountability dashboard | E11: 1.25 | F11: 1.25 | G11: 1.25 | H11: 1.25 | I11: =SUM(E11:H11) -> 5 | J11: =I11*100000 -> 500000
A12: Project Rakshak | B12: Institutionalisation | C12: Post-intervention impact audits | D12: Before/after assessment at implemented sites | E12: 0 | F12: 2 | G12: 3 | H12: 3 | I12: =SUM(E12:H12) -> 8 | J12: =I12*100000 -> 800000
A13: Project Rakshak | B13: Engagement & Visibility | C13: Rakshak Finale + national awards | D13: Annual finale event + prize pool for top teams (trimmed from 50L in prior draft) | E13: 0 | F13: 0 | G13: 10 | H13: 20 | I13: =SUM(E13:H13) -> 30 | J13: =I13*100000 -> 3000000
A14: Project Rakshak | B14: Engagement & Visibility | C14: Travel & field logistics | D14: Team + mentor travel to anchor districts and audit sites | E14: 3 | F14: 3 | G14: 2 | H14: 2 | I14: =SUM(E14:H14) -> 10 | J14: =I14*100000 -> 1000000
A15: Project Rakshak | B15: Engagement & Visibility | C15: Media, documentation & communication | D15: Site stories, audit report design, public communication | E15: 3 | F15: 4 | G15: 4 | H15: 4 | I15: =SUM(E15:H15) -> 15 | J15: =I15*100000 -> 1500000
A16: Project Rakshak | B16: Engagement & Visibility | C16: DRSC & stakeholder engagement | D16: 12+ DRSC presentations; district administration consultations | E16: 2 | F16: 3 | G16: 2 | H16: 2 | I16: =SUM(E16:H16) -> 9 | J16: =I16*100000 -> 900000
... A44: Contingency | B44: Contingency | C44: Contingency reserve (4%) | D44: 4% of Rs 6.00 Cr total budget; buffer for partner-driven and unbudgeted costs | E44: 6 | F44: 6 | G44: 6 | H44: 6 | I44: =SUM(E44:H44) -> 24 | J44: =I44*100000 -> 2400000
A45: GRAND TOTAL | E45: =SUM(E5:E44) -> 122.5 | F45: =SUM(F5:F44) -> 161 | G45: =SUM(G5:G44) -> 164.5 | H45: =SUM(H5:H44) -> 152 | I45: =SUM(I5:I44) -> 600 | J45: =SUM(J5:J44) -> 60000000

Sheet Notes & Assumptions
A1: HOW TO USE THIS WORKBOOK
A2: Editable cells | B2: Blue-font cells on 'Budget Detail' (quarterly amounts, Rs Lakh) are the only inputs. All totals, the summary sheet, and %s recalculate automatically.
A3: Structure | B3: Each line = Vertical > Programme > Line Item with an explicit basis of estimate (unit x rate wherever available).
A4: Period | B4: Q1 = Jul-Sep 2026, Q2 = Oct-Dec 2026, Q3 = Jan-Mar 2027, Q4 = Apr-Jun 2027.
A6: KEY ASSUMPTIONS (from AOP source documents; verify before board sign-off)
A7: Rakshak | B7: 100 student teams @ Rs 36K (Cohort 2 AOP); 25 mentors @ Rs 24K; Track C = ~40 sites @ ~Rs 25K/site RSA fee (rate assumed - confirm with empanelment EOIs); NGO Track B grants Rs 12L.
A8: Civic & GovTech | B8: NEW vertical, set at exactly Rs 1.00 Cr per Akhtar's instruction. Target: SATARK scaled to 30 cities by Jun 2027 (live today: Jaipur + Bengaluru) + four open data products + exploration of new govtech/DPG opportunities. SATARK docs contain NO cost data - every line is a planning assumption. CRITICAL: Rs 1 Cr funds the software/integration side only; a 30-city rollout assumes city-side infra (ANPR cameras, billboards) is funded by police/partners. Validate before board sign-off.
A9: Hit & Run | B9: Sized to the Rs 47-66L envelope in the Crash Claim AOP review deck (set at Rs 60L). Vertical lead compensation assumed inside 'Vertical team' line, per org policy.
A10: Bets (Seed Fund) | B10: School Safety Index and Gig Rider Safety are no longer funded programmes this year - each carries a Rs 10L seed, released only against a board-approved pilot/study design. If a bet proves out, it returns as a funded Year 3 programme.
A11: Marketing | B11: 'Safety is the New Swag' campaign consolidated at Rs 60L: all four campaign pillars now carry budgets (prior draft had 3 of 4 pillars at Rs 0) + Rs 8L campaign management (was an untagged Rs 30L 'people cost').
A12: Trust Admin | B12: Salaries Rs 78L; IRSC institutional charge Rs 42L (=~Rs 3.5L/mo, matches mid-year actuals); IT+AI tools consolidated at Rs 14L.
A13: Contingency | B13: Exactly 4% of Rs 6.00 Cr = Rs 24L (prior draft said '4%' but held Rs 20L = 3.2%).
A15: CHANGES IN v4 (vs v3, Jul 2026 - per Akhtar's restructure instruction)
A16: 1 | B16: School Safety Index removed as a funded vertical (was Rs 100L) - moved to the Bets seed fund at Rs 10L.
A17: 2 | B17: Gig Rider Safety removed as a funded vertical (was Rs 20L) - moved to the Bets seed fund at Rs 10L.
A18: 3 | B18: NEW Civic & GovTech (SATARK) vertical added at exactly Rs 100L: SATARK platform Rs 80L + data-stack public goods Rs 20L.
A19: 4 | B19: Grand total unchanged at Rs 600.0L; programme spend unchanged at Rs 425L (~71%); contingency unchanged at Rs 24L (4%).
A21: CHANGES vs 'Budget Bifurcation_v2' (prior draft, Rs 6.20 Cr - carried from v3)
A22: 1 | B22: Total rebalanced from Rs 619.7L to exactly Rs 600.0L.
A23: 2 | B23: Rakshak trimmed Rs 210L -> Rs 185L: Finale+prizes 50->30L, media 25->15L; consortium/manual line added (institutionalisation focus).
A24: 3 | B24: Marketing: 3 campaign pillars had descriptions but Rs 0 budget; all 4 pillars now funded; Rs 30L untagged people cost reduced to Rs 8L campaign management.
A25: 4 | B25: Missing 'Rs Lakh' values fixed (salaries, AI tools, marketing people cost had blank lakh column).
A26: 5 | B26: Every line now has quarterly phasing + basis of estimate; summary + quarterly rollups are formula-driven.
A27: 6 | B27: H&R kept at Rs 60L (within the Rs 47-66L envelope from the vertical AOP deck).
