Workbook

Sheet Line Items
A1: CFI · AOP 2026–27 · Budget line items with project mapping (edit the Project column — every other tab recalculates)
A2: Vertical | B2: Activity | C2: Budget (₹) | D2: In lacs | E2: Project | F2: Notes / assumptions
A3: Trust Admin | B3: Branding & Outreach | C3: 100000 | D3: =C3/100000 | E3: Org Backbone
A4: Trust Admin | B4: Capacity Building and Consultation | C4: 3600000 | D4: =C4/100000 | E4: Org Backbone | F4: Expert / leadership / consultation fees — shared across projects
A5: Trust Admin | B5: Employee Benefits | C5: 100000 | D5: =C5/100000 | E5: Org Backbone
A6: Trust Admin | B6: Intervention audit (M&E) | C6: 500000 | D6: =C6/100000 | E6: Org Backbone | F6: M&E of interventions — could move to Rakshak
A7: Trust Admin | B7: IT hardware cost | C7: 0 | D7: =C7/100000 | E7: Org Backbone
A8: Trust Admin | B8: Marketing material | C8: 100000 | D8: =C8/100000 | E8: Org Backbone
A9: Trust Admin | B9: Office space (Virtual) | C9: 100000 | D9: =C9/100000 | E9: Org Backbone
A10: Trust Admin | B10: Office utilities | C10: 0 | D10: =C10/100000 | E10: Org Backbone
A11: Trust Admin | B11: Reporting and Compliance | C11: 500000 | D11: =C11/100000 | E11: Org Backbone
A12: Trust Admin | B12: Salaries & Benefits | C12: 3100000 | D12: =C12/100000 | E12: Org Backbone | F12: Core team — realistically splits across projects; parked in backbone
A13: Trust Admin | B13: Travel & Networking | C13: 500000 | D13: =C13/100000 | E13: Org Backbone
A14: Trust Admin | B14: Website Development & Hosting | C14: 100000 | D14: =C14/100000 | E14: Org Backbone
A15: Technology | B15: Collaboration with Google (Maps) | C15: 300000 | D15: =C15/100000 | E15: Project Rakshak | F15: ★ Defect repository / Maps — mapped to Rakshak; could be SATARK
A16: Technology | B16: Community Action via Mobile App | C16: 1000000 | D16: =C16/100000 | E16: Civic & GovTech (SATARK) | F16: ★ Citizen-reporting app — mapped to SATARK/Civic Tech
A17: Technology | B17: National Road Safety Hackathon + Good Samaritan awards | C17: 5000000 | D17: =C17/100000 | E17: Campaign & Comms | F17: ★ Large public event — mapped to Campaign; part GovTech
A18: Technology | B18: Product development: Safekart / Hackathon incubation | C18: 800000 | D18: =C18/100000 | E18: Bets — New Products | F18: ★ New-product incubation — mapped to Bets
A19: Education | B19: Safety is the new swag (CARS24 campaign) | C19: 4000000 | D19: =C19/100000 | E19: Campaign & Comms
A20: Enabler - Community Building | B20: Safer Mobility Impact Fellowship | C20: 3000000 | D20: =C20/100000 | E20: Org Backbone | F20: ★ Talent pipeline feeding all projects — parked in backbone
A21: Infrastructure | B21: Infrastructure Internship & School Safety Zone | C21: 2800000 | D21: =C21/100000 | E21: Project Rakshak | F21: ★ Includes School Safety Index — carve SSI out here when ready
A22: Policy | B22: Strengthening Road Safety Regulations via RTI/PIL | C22: 2200000 | D22: =C22/100000 | E22: Policy & Advocacy | F22: Part of this research also feeds compensation
A23: Post-emergency care | B23: Study on Cashless Treatment & Compensation (Delhi NCR) | C23: 1200000 | D23: =C23/100000 | E23: Hit & Run Compensation
A24: Contingency (4%) | B24: Contingency cost | C24: 1000000 | D24: =C24/100000 | E24: Contingency
A25: Grand Total | C25: =SUM(C3:C24) | D25: =C25/100000

Sheet By Project
A1: AOP 2026–27 · Budget by project
A2: Project | B2: Budget (₹) | C2: In lacs | D2: % of total
A3: Project Rakshak | B3: =SUMIF('Line Items'!$E$3:$E$24,A3,'Line Items'!$C$3:$C$24) | C3: =B3/100000 | D3: =B3/$B$13
A4: Hit & Run Compensation | B4: =SUMIF('Line Items'!$E$3:$E$24,A4,'Line Items'!$C$3:$C$24) | C4: =B4/100000 | D4: =B4/$B$13
A5: Civic & GovTech (SATARK) | B5: =SUMIF('Line Items'!$E$3:$E$24,A5,'Line Items'!$C$3:$C$24) | C5: =B5/100000 | D5: =B5/$B$13
A6: Gig Rider Safety | B6: =SUMIF('Line Items'!$E$3:$E$24,A6,'Line Items'!$C$3:$C$24) | C6: =B6/100000 | D6: =B6/$B$13
A7: School Safety Index | B7: =SUMIF('Line Items'!$E$3:$E$24,A7,'Line Items'!$C$3:$C$24) | C7: =B7/100000 | D7: =B7/$B$13
A8: Campaign & Comms | B8: =SUMIF('Line Items'!$E$3:$E$24,A8,'Line Items'!$C$3:$C$24) | C8: =B8/100000 | D8: =B8/$B$13
A9: Policy & Advocacy | B9: =SUMIF('Line Items'!$E$3:$E$24,A9,'Line Items'!$C$3:$C$24) | C9: =B9/100000 | D9: =B9/$B$13
A10: Bets — New Products | B10: =SUMIF('Line Items'!$E$3:$E$24,A10,'Line Items'!$C$3:$C$24) | C10: =B10/100000 | D10: =B10/$B$13
A11: Org Backbone | B11: =SUMIF('Line Items'!$E$3:$E$24,A11,'Line Items'!$C$3:$C$24) | C11: =B11/100000 | D11: =B11/$B$13
A12: Contingency | B12: =SUMIF('Line Items'!$E$3:$E$24,A12,'Line Items'!$C$3:$C$24) | C12: =B12/100000 | D12: =B12/$B$13
A13: Grand Total | B13: =SUM(B3:B12) | C13: =B13/100000 | D13: =B13/$B$13

Sheet Project x Vertical
A1: AOP 2026–27 · Project × Vertical matrix (verticals preserved; re-cut by project)
A2: Project ↓ / Vertical → | B2: Trust Admin | C2: Technology | D2: Education | E2: Enabler - Community Building | F2: Infrastructure | G2: Policy | H2: Post-emergency care | I2: Contingency (4%) | J2: Project total
A3: Project Rakshak | B3: =SUMIFS('Line Items'!$C$3:$C$24,'Line Items'!$E$3:$E$24,$A3,'Line Items'!$A$3:$A$24,B$2) | C3: =SUMIFS('Line Items'!$C$3:$C$24,'Line Items'!$E$3:$E$24,$A3,'Line Items'!$A$3:$A$24,C$2) | D3: =SUMIFS('Line Items'!$C$3:$C$24,'Line Items'!$E$3:$E$24,$A3,'Line Items'!$A$3:$A$24,D$2) | E3: =SUMIFS('Line Items'!$C$3:$C$24,'Line Items'!$E$3:$E$24,$A3,'Line Items'!$A$3:$A$24,E$2) | F3: =SUMIFS('Line Items'!$C$3:$C$24,'Line Items'!$E$3:$E$24,$A3,'Line Items'!$A$3:$A$24,F$2) | G3: =SUMIFS('Line Items'!$C$3:$C$24,'Line Items'!$E$3:$E$24,$A3,'Line Items'!$A$3:$A$24,G$2) | H3: =SUMIFS('Line Items'!$C$3:$C$24,'Line Items'!$E$3:$E$24,$A3,'Line Items'!$A$3:$A$24,H$2) | I3: =SUMIFS('Line Items'!$C$3:$C$24,'Line Items'!$E$3:$E$24,$A3,'Line Items'!$A$3:$A$24,I$2) | J3: =SUM(B3:I3)
A4: Hit & Run Compensation | B4: =SUMIFS('Line Items'!$C$3:$C$24,'Line Items'!$E$3:$E$24,$A4,'Line Items'!$A$3:$A$24,B$2) | C4: =SUMIFS('Line Items'!$C$3:$C$24,'Line Items'!$E$3:$E$24,$A4,'Line Items'!$A$3:$A$24,C$2) | D4: =SUMIFS('Line Items'!$C$3:$C$24,'Line Items'!$E$3:$E$24,$A4,'Line Items'!$A$3:$A$24,D$2) | E4: =SUMIFS('Line Items'!$C$3:$C$24,'Line Items'!$E$3:$E$24,$A4,'Line Items'!$A$3:$A$24,E$2) | F4: =SUMIFS('Line Items'!$C$3:$C$24,'Line Items'!$E$3:$E$24,$A4,'Line Items'!$A$3:$A$24,F$2) | G4: =SUMIFS('Line Items'!$C$3:$C$24,'Line Items'!$E$3:$E$24,$A4,'Line Items'!$A$3:$A$24,G$2) | H4: =SUMIFS('Line Items'!$C$3:$C$24,'Line Items'!$E$3:$E$24,$A4,'Line Items'!$A$3:$A$24,H$2) | I4: =SUMIFS('Line Items'!$C$3:$C$24,'Line Items'!$E$3:$E$24,$A4,'Line Items'!$A$3:$A$24,I$2) | J4: =SUM(B4:I4)
A5: Civic & GovTech (SATARK) | B5: =SUMIFS('Line Items'!$C$3:$C$24,'Line Items'!$E$3:$E$24,$A5,'Line Items'!$A$3:$A$24,B$2) | C5: =SUMIFS('Line Items'!$C$3:$C$24,'Line Items'!$E$3:$E$24,$A5,'Line Items'!$A$3:$A$24,C$2) | D5: =SUMIFS('Line Items'!$C$3:$C$24,'Line Items'!$E$3:$E$24,$A5,'Line Items'!$A$3:$A$24,D$2) | E5: =SUMIFS('Line Items'!$C$3:$C$24,'Line Items'!$E$3:$E$24,$A5,'Line Items'!$A$3:$A$24,E$2) | F5: =SUMIFS('Line Items'!$C$3:$C$24,'Line Items'!$E$3:$E$24,$A5,'Line Items'!$A$3:$A$24,F$2) | G5: =SUMIFS('Line Items'!$C$3:$C$24,'Line Items'!$E$3:$E$24,$A5,'Line Items'!$A$3:$A$24,G$2) | H5: =SUMIFS('Line Items'!$C$3:$C$24,'Line Items'!$E$3:$E$24,$A5,'Line Items'!$A$3:$A$24,H$2) | I5: =SUMIFS('Line Items'!$C$3:$C$24,'Line Items'!$E$3:$E$24,$A5,'Line Items'!$A$3:$A$24,I$2) | J5: =SUM(B5:I5)
A6: Gig Rider Safety | B6: =SUMIFS('Line Items'!$C$3:$C$24,'Line Items'!$E$3:$E$24,$A6,'Line Items'!$A$3:$A$24,B$2) | C6: =SUMIFS('Line Items'!$C$3:$C$24,'Line Items'!$E$3:$E$24,$A6,'Line Items'!$A$3:$A$24,C$2) | D6: =SUMIFS('Line Items'!$C$3:$C$24,'Line Items'!$E$3:$E$24,$A6,'Line Items'!$A$3:$A$24,D$2) | E6: =SUMIFS('Line Items'!$C$3:$C$24,'Line Items'!$E$3:$E$24,$A6,'Line Items'!$A$3:$A$24,E$2) | F6: =SUMIFS('Line Items'!$C$3:$C$24,'Line Items'!$E$3:$E$24,$A6,'Line Items'!$A$3:$A$24,F$2) | G6: =SUMIFS('Line Items'!$C$3:$C$24,'Line Items'!$E$3:$E$24,$A6,'Line Items'!$A$3:$A$24,G$2) | H6: =SUMIFS('Line Items'!$C$3:$C$24,'Line Items'!$E$3:$E$24,$A6,'Line Items'!$A$3:$A$24,H$2) | I6: =SUMIFS('Line Items'!$C$3:$C$24,'Line Items'!$E$3:$E$24,$A6,'Line Items'!$A$3:$A$24,I$2) | J6: =SUM(B6:I6)
A7: School Safety Index | B7: =SUMIFS('Line Items'!$C$3:$C$24,'Line Items'!$E$3:$E$24,$A7,'Line Items'!$A$3:$A$24,B$2) | C7: =SUMIFS('Line Items'!$C$3:$C$24,'Line Items'!$E$3:$E$24,$A7,'Line Items'!$A$3:$A$24,C$2) | D7: =SUMIFS('Line Items'!$C$3:$C$24,'Line Items'!$E$3:$E$24,$A7,'Line Items'!$A$3:$A$24,D$2) | E7: =SUMIFS('Line Items'!$C$3:$C$24,'Line Items'!$E$3:$E$24,$A7,'Line Items'!$A$3:$A$24,E$2) | F7: =SUMIFS('Line Items'!$C$3:$C$24,'Line Items'!$E$3:$E$24,$A7,'Line Items'!$A$3:$A$24,F$2) | G7: =SUMIFS('Line Items'!$C$3:$C$24,'Line Items'!$E$3:$E$24,$A7,'Line Items'!$A$3:$A$24,G$2) | H7: =SUMIFS('Line Items'!$C$3:$C$24,'Line Items'!$E$3:$E$24,$A7,'Line Items'!$A$3:$A$24,H$2) | I7: =SUMIFS('Line Items'!$C$3:$C$24,'Line Items'!$E$3:$E$24,$A7,'Line Items'!$A$3:$A$24,I$2) | J7: =SUM(B7:I7)
A8: Campaign & Comms | B8: =SUMIFS('Line Items'!$C$3:$C$24,'Line Items'!$E$3:$E$24,$A8,'Line Items'!$A$3:$A$24,B$2) | C8: =SUMIFS('Line Items'!$C$3:$C$24,'Line Items'!$E$3:$E$24,$A8,'Line Items'!$A$3:$A$24,C$2) | D8: =SUMIFS('Line Items'!$C$3:$C$24,'Line Items'!$E$3:$E$24,$A8,'Line Items'!$A$3:$A$24,D$2) | E8: =SUMIFS('Line Items'!$C$3:$C$24,'Line Items'!$E$3:$E$24,$A8,'Line Items'!$A$3:$A$24,E$2) | F8: =SUMIFS('Line Items'!$C$3:$C$24,'Line Items'!$E$3:$E$24,$A8,'Line Items'!$A$3:$A$24,F$2) | G8: =SUMIFS('Line Items'!$C$3:$C$24,'Line Items'!$E$3:$E$24,$A8,'Line Items'!$A$3:$A$24,G$2) | H8: =SUMIFS('Line Items'!$C$3:$C$24,'Line Items'!$E$3:$E$24,$A8,'Line Items'!$A$3:$A$24,H$2) | I8: =SUMIFS('Line Items'!$C$3:$C$24,'Line Items'!$E$3:$E$24,$A8,'Line Items'!$A$3:$A$24,I$2) | J8: =SUM(B8:I8)
A9: Policy & Advocacy | B9: =SUMIFS('Line Items'!$C$3:$C$24,'Line Items'!$E$3:$E$24,$A9,'Line Items'!$A$3:$A$24,B$2) | C9: =SUMIFS('Line Items'!$C$3:$C$24,'Line Items'!$E$3:$E$24,$A9,'Line Items'!$A$3:$A$24,C$2) | D9: =SUMIFS('Line Items'!$C$3:$C$24,'Line Items'!$E$3:$E$24,$A9,'Line Items'!$A$3:$A$24,D$2) | E9: =SUMIFS('Line Items'!$C$3:$C$24,'Line Items'!$E$3:$E$24,$A9,'Line Items'!$A$3:$A$24,E$2) | F9: =SUMIFS('Line Items'!$C$3:$C$24,'Line Items'!$E$3:$E$24,$A9,'Line Items'!$A$3:$A$24,F$2) | G9: =SUMIFS('Line Items'!$C$3:$C$24,'Line Items'!$E$3:$E$24,$A9,'Line Items'!$A$3:$A$24,G$2) | H9: =SUMIFS('Line Items'!$C$3:$C$24,'Line Items'!$E$3:$E$24,$A9,'Line Items'!$A$3:$A$24,H$2) | I9: =SUMIFS('Line Items'!$C$3:$C$24,'Line Items'!$E$3:$E$24,$A9,'Line Items'!$A$3:$A$24,I$2) | J9: =SUM(B9:I9)
A10: Bets — New Products | B10: =SUMIFS('Line Items'!$C$3:$C$24,'Line Items'!$E$3:$E$24,$A10,'Line Items'!$A$3:$A$24,B$2) | C10: =SUMIFS('Line Items'!$C$3:$C$24,'Line Items'!$E$3:$E$24,$A10,'Line Items'!$A$3:$A$24,C$2) | D10: =SUMIFS('Line Items'!$C$3:$C$24,'Line Items'!$E$3:$E$24,$A10,'Line Items'!$A$3:$A$24,D$2) | E10: =SUMIFS('Line Items'!$C$3:$C$24,'Line Items'!$E$3:$E$24,$A10,'Line Items'!$A$3:$A$24,E$2) | F10: =SUMIFS('Line Items'!$C$3:$C$24,'Line Items'!$E$3:$E$24,$A10,'Line Items'!$A$3:$A$24,F$2) | G10: =SUMIFS('Line Items'!$C$3:$C$24,'Line Items'!$E$3:$E$24,$A10,'Line Items'!$A$3:$A$24,G$2) | H10: =SUMIFS('Line Items'!$C$3:$C$24,'Line Items'!$E$3:$E$24,$A10,'Line Items'!$A$3:$A$24,H$2) | I10: =SUMIFS('Line Items'!$C$3:$C$24,'Line Items'!$E$3:$E$24,$A10,'Line Items'!$A$3:$A$24,I$2) | J10: =SUM(B10:I10)
A11: Org Backbone | B11: =SUMIFS('Line Items'!$C$3:$C$24,'Line Items'!$E$3:$E$24,$A11,'Line Items'!$A$3:$A$24,B$2) | C11: =SUMIFS('Line Items'!$C$3:$C$24,'Line Items'!$E$3:$E$24,$A11,'Line Items'!$A$3:$A$24,C$2) | D11: =SUMIFS('Line Items'!$C$3:$C$24,'Line Items'!$E$3:$E$24,$A11,'Line Items'!$A$3:$A$24,D$2) | E11: =SUMIFS('Line Items'!$C$3:$C$24,'Line Items'!$E$3:$E$24,$A11,'Line Items'!$A$3:$A$24,E$2) | F11: =SUMIFS('Line Items'!$C$3:$C$24,'Line Items'!$E$3:$E$24,$A11,'Line Items'!$A$3:$A$24,F$2) | G11: =SUMIFS('Line Items'!$C$3:$C$24,'Line Items'!$E$3:$E$24,$A11,'Line Items'!$A$3:$A$24,G$2) | H11: =SUMIFS('Line Items'!$C$3:$C$24,'Line Items'!$E$3:$E$24,$A11,'Line Items'!$A$3:$A$24,H$2) | I11: =SUMIFS('Line Items'!$C$3:$C$24,'Line Items'!$E$3:$E$24,$A11,'Line Items'!$A$3:$A$24,I$2) | J11: =SUM(B11:I11)
A12: Contingency | B12: =SUMIFS('Line Items'!$C$3:$C$24,'Line Items'!$E$3:$E$24,$A12,'Line Items'!$A$3:$A$24,B$2) | C12: =SUMIFS('Line Items'!$C$3:$C$24,'Line Items'!$E$3:$E$24,$A12,'Line Items'!$A$3:$A$24,C$2) | D12: =SUMIFS('Line Items'!$C$3:$C$24,'Line Items'!$E$3:$E$24,$A12,'Line Items'!$A$3:$A$24,D$2) | E12: =SUMIFS('Line Items'!$C$3:$C$24,'Line Items'!$E$3:$E$24,$A12,'Line Items'!$A$3:$A$24,E$2) | F12: =SUMIFS('Line Items'!$C$3:$C$24,'Line Items'!$E$3:$E$24,$A12,'Line Items'!$A$3:$A$24,F$2) | G12: =SUMIFS('Line Items'!$C$3:$C$24,'Line Items'!$E$3:$E$24,$A12,'Line Items'!$A$3:$A$24,G$2) | H12: =SUMIFS('Line Items'!$C$3:$C$24,'Line Items'!$E$3:$E$24,$A12,'Line Items'!$A$3:$A$24,H$2) | I12: =SUMIFS('Line Items'!$C$3:$C$24,'Line Items'!$E$3:$E$24,$A12,'Line Items'!$A$3:$A$24,I$2) | J12: =SUM(B12:I12)
A13: Vertical total | B13: =SUM(B3:B12) | C13: =SUM(C3:C12) | D13: =SUM(D3:D12) | E13: =SUM(E3:E12) | F13: =SUM(F3:F12) | G13: =SUM(G3:G12) | H13: =SUM(H3:H12) | I13: =SUM(I3:I12) | J13: =SUM(J3:J12)

Sheet By Vertical (tie-out)
A1: Tie-out · original vertical totals (must still equal ₹3.0 Cr)
A2: Vertical | B2: Budget (₹) | C2: In lacs
A3: Trust Admin | B3: =SUMIF('Line Items'!$A$3:$A$24,A3,'Line Items'!$C$3:$C$24) | C3: =B3/100000
A4: Technology | B4: =SUMIF('Line Items'!$A$3:$A$24,A4,'Line Items'!$C$3:$C$24) | C4: =B4/100000
A5: Education | B5: =SUMIF('Line Items'!$A$3:$A$24,A5,'Line Items'!$C$3:$C$24) | C5: =B5/100000
A6: Enabler - Community Building | B6: =SUMIF('Line Items'!$A$3:$A$24,A6,'Line Items'!$C$3:$C$24) | C6: =B6/100000
A7: Infrastructure | B7: =SUMIF('Line Items'!$A$3:$A$24,A7,'Line Items'!$C$3:$C$24) | C7: =B7/100000
A8: Policy | B8: =SUMIF('Line Items'!$A$3:$A$24,A8,'Line Items'!$C$3:$C$24) | C8: =B8/100000
A9: Post-emergency care | B9: =SUMIF('Line Items'!$A$3:$A$24,A9,'Line Items'!$C$3:$C$24) | C9: =B9/100000
A10: Contingency (4%) | B10: =SUMIF('Line Items'!$A$3:$A$24,A10,'Line Items'!$C$3:$C$24) | C10: =B10/100000
A11: Grand Total | B11: =SUM(B3:B10) | C11: =B11/100000

Sheet Notes
A1: CFI · AOP 2026–27 — project bifurcation (first pass)
A3: Source: 'CFI - AOP (2026-2027)' Google Sheet, quarterly-phased tab. Total ₹3,00,00,000 (₹3.0 Cr / 300 lacs).
A4: The 8 verticals are kept exactly as in the sheet. The Project column on 'Line Items' is the only thing you edit —
A5: every other tab recalculates from it. Reassign a row's project and the pivots + matrix update automatically.
A7: Judgement calls to confirm (marked ★ in the Notes column):
A8: • Collaboration with Google (Maps), ₹3 L → Project Rakshak (defect repository / Maps). Could sit under SATARK.
A9: • Community Action via Mobile App, ₹10 L → SATARK / Civic Tech. Could be a Campaign asset.
A10: • National Hackathon + Good Samaritan awards, ₹50 L → Campaign & Comms. Part of it is GovTech talent-sourcing.
A11: • Safekart / incubation, ₹8 L → Bets (new products).
A12: • Safer Mobility Impact Fellowship, ₹30 L → Org Backbone (talent feeding all projects). Could be split across projects.
A13: • Salaries & Benefits ₹31 L and Capacity Building ₹36 L are shared core costs, parked in Org Backbone for now.
A14: • Infrastructure Internship ₹28 L currently bundles the School Safety Zone — School Safety Index has no separate line yet.
... A22: add the GL cost-category view (Professional fees, Salary & Incentives, Audit & Compliance, Tech Infra, Marketing, Rent).
