Workbook

Sheet AOP Bifurcation
A1: Vertical | B1: Category (focus area) | C1: Cost group (high-level) | D1: Further bifurcation (line item) | E1: Description | F1: Budget allocated | G1: Remarks for Keshav — tagging & finance notes
A2: Infrastructure | B2: Project Rakshak | C2: Institutional track | D2: Student team stipends | E2: ₹36,000/team on completion · ~90 sites | F2: 3240000 | G2: GL: Salary & Incentives (stipends). Milestone-linked — accrue quarterly, release on sign-off. Volume driver = # teams; true-up to actual cohort. Confirm TDS on student stipends with CA. Programme (restricted).
A3: Infrastructure | B3: Project Rakshak | C3: Institutional track | D3: Expert mentor honoraria | E3: Faculty & road-safety expert mentors | F3: 1300000 | G3: GL: Professional fees. TDS u/s 194J (10%). Per-session/mentor — keep engagement letters.
A4: Infrastructure | B4: Project Rakshak | C4: Institutional track | D4: Campus outreach, onboarding & merchandise | E4: Chapter mobilisation, IDs, kits, ads | F4: 960000 | G4: GL: Marketing & Branding + Office. Mixed (merch/print + digital ads + travel). Claim GST input where invoiced.
A5: Infrastructure | B5: Project Rakshak | C5: NGO partner track | D5: NGO field-team engagement | E5: ~20 sites via NGO partners | F5: 2000000 | G5: GL: Professional fees / grant-to-partner. Confirm TDS 194C vs grant treatment. Milestone per site. Restricted.
A6: Infrastructure | B6: Project Rakshak | C6: NGO partner track | D6: CFI desk + 10–15% physical re-checks | E6: QA on NGO submissions | F6: 500000 | G6: GL: Travel + Professional fees. Mostly staff time + travel; book travel to Travel head.
A7: Infrastructure | B7: Project Rakshak | C7: Certified RSA track | D7: CRRI-certified auditor fees (IRC SP:88) | E7: ~40 sites, NHAI-usable audits | F7: 4500000 | G7: GL: Professional fees. Largest single vendor line. TDS 194J + GST input. Milestone/per-audit — keep PO + deliverable.
A8: Infrastructure | B8: Project Rakshak | C8: Expert Consortium & Audit Manual | D8: Expert Consortium (4 meetings) | E8: Sep / Dec / Mar / Jun sittings | F8: 1000000 | G8: GL: Professional fees (194J) + Travel + venue. Accrue per meeting.
A9: Infrastructure | B9: Project Rakshak | C9: Expert Consortium & Audit Manual | D9: Audit Manual v1.0 production | E9: Authoring, design, print | F9: 800000 | G9: GL: Professional fees + print. Programme opex; GST input on print. Mostly one-time.
A10: Technology | B10: Project Rakshak | C10: Public dashboard | D10: Public accountability dashboard | E10: Build + hosting; identification→implementation tracker | F10: 1200000 | G10: GL: Tech Infra. Split build (one-time) vs hosting (recurring). If in-house, it is staff time — confirm vendor vs internal.
A11: Infrastructure | B11: Project Rakshak | C11: Programme management & field ops | D11: Programme management (staff allocation) | E11: PM + coordination time on Rakshak | F11: 1800000 | G11: GL: Salary & Incentives — ALLOCATION, not a new payout. Ensure NOT double-counted in Trust Admin salaries.
A12: Infrastructure | B12: Project Rakshak | C12: Programme management & field ops | D12: Field travel & logistics | E12: Site visits, DRSC meetings | F12: 700000 | G12: GL: Travel. Reimbursements, no TDS.
A13: Infrastructure | B13: Project Rakshak | C13: Programme management & field ops | D13: National forum & DRSC presentations | E13: 12+ DRSC presentations, year-end forum | F13: 500000 | G13: GL: Events + Travel. Venue & logistics — GST input on vendor invoices.
... A32: Education | B32: Marketing Campaign | C32: Offline awareness | D32: OOH in 3–4 cities | E32: Billboards, transit | F32: 1000000 | G32: GL: Marketing & Branding. OOH media buy — 194C + GST input.
A33: Education | B33: Marketing Campaign | C33: Offline awareness | D33: Guerilla installations & event co-branding | F33: 500000 | G33: GL: Marketing & Branding / Events.
A34: Education | B34: Marketing Campaign | C34: Community mobilization | D34: College competitions & app-based engagement | E34: Real-life stories | F34: 1000000 | G34: GL: Marketing + Office. Keep winner records for prize payouts.
A35: Infrastructure | B35: Bets — School Safety Index | C35: School Safety Index (seed) | D35: IRC:SP:32 rubric validation & Zone Captain pilot | E35: ~100 school zones in one city | F35: 700000 | G35: GL: Professional fees + Travel. SEED — release ONLY against board-approved design (stage gate). Ring-fence at ₹0.10 Cr.
A36: Infrastructure | B36: Bets — School Safety Index | C36: School Safety Index (seed) | D36: Per-school costing & board-ready design | E36: Gate to Year-3 funded index | F36: 300000 | G36: GL: Professional fees. SEED. Deliverable = board paper.
A37: Policy | B37: Bets — Gig Rider | C37: Gig Rider (seed) | D37: Gig crash-data scoping study | E37: National study parked till model proven | F37: 600000 | G37: GL: Professional fees. SEED — researcher fees 194J. Ring-fence at ₹0.10 Cr.
A38: Policy | B38: Bets — Gig Rider | C38: Gig Rider (seed) | D38: Platform + OMI Foundation engagements | E38: 3+ platforms at the table | F38: 400000 | G38: GL: Travel + Professional fees. SEED. Relationship-building.
A39: Trust Admin | B39: Org Backbone | C39: Core team salaries | D39: Core team salaries & benefits | E39: Aggregate core staff (individual figures withheld) | F39: 4200000 | G39: GL: Salary & Incentives. Core/shared payroll ONLY (not cross-charged to programmes). Ensure programme staff-allocations are NOT double-counted. Monthly; TDS 192, PF/ESI.
A40: Enabler | B40: Org Backbone | C40: Fellowship (SMIF) | D40: Safer Mobility Impact Fellowship | E40: ~6 fellows across tracks (aggregate) | F40: 3600000 | G40: GL: Salary & Incentives (fellowship). HRMS fixed-term agreements. Recurring monthly. Individual amounts confidential. If a fellow is dedicated to a programme, consider cross-charging it.
A41: Trust Admin | B41: Org Backbone | C41: IRSC institutional support | D41: IRSC institutional support & expert consultation | E41: Shared expert/leadership | F41: 4200000 | G41: GL: Professional fees. TDS 194J + GST. IRSC is a related party — confirm inter-entity treatment; keep MoU.
A42: Technology | B42: Org Backbone | C42: IT, SaaS & AI tooling | D42: AI tooling — Claude (Team) + Codex / AI subscriptions | E42: AI assistants for build/research/ops | F42: 600000 | G42: GL: Tech Infra (software subscriptions). ← dedicated AI-tooling line. Recurring monthly, mostly USD (Anthropic/OpenAI) — GST under RCM on import of service (pay & claim) + forex/card fees. Receipts already reaching finance.
A43: Technology | B43: Org Backbone | C43: IT, SaaS & AI tooling | D43: Google Workspace & email | E43: Per-seat | F43: 300000 | G43: GL: Tech Infra. Recurring per-seat — scales with headcount. RCM watch.
A44: Technology | B44: Org Backbone | C44: IT, SaaS & AI tooling | D44: Slack & collaboration | E44: Per-seat | F44: 200000 | G44: GL: Tech Infra. Recurring per-seat. RCM watch.
A45: Technology | B45: Org Backbone | C45: IT, SaaS & AI tooling | D45: HRMS 'CFI People' & other SaaS | F45: 200000 | G45: GL: Tech Infra. HRMS + misc SaaS. Recurring.
A46: Technology | B46: Org Backbone | C46: IT, SaaS & AI tooling | D46: Cloud, hosting & domains | E46: Not product-specific | F46: 100000 | G46: GL: Tech Infra. Domains/hosting. Recurring.
A47: Trust Admin | B47: Org Backbone | C47: M&E & audit | D47: M&E, statutory & impact audit | E47: Statutory audit + M&E | F47: 600000 | G47: GL: Audit & Compliance. TDS 194J. Year-end weighted.
A48: Trust Admin | B48: Org Backbone | C48: Overheads (travel/branding/compliance) | D48: Travel, branding & compliance | E48: Org travel, branding, compliance | F48: 1100000 | G48: GL: mixed (Travel + Marketing + Compliance). Split into 3 lines if you want cleaner cost-head pivots.
A49: Contingency | B49: Contingency | C49: Contingency reserve | D49: Contingency reserve (4%) | E49: Held against programme + admin spend | F49: 2400000 | G49: GL: Contingency (do NOT pre-allocate). Release only on approved overruns and RE-TAG to the actual head when spent.

Sheet Summary
A1: Reconciliation — ties to the AOP (₹6.00 Cr)
A2: Grand total | B2: =SUM('AOP Bifurcation'!$F$2:$F$49) | C2: expected ₹6,00,00,000
A4: By Vertical (functional)
A5: Vertical | B5: Budget (₹) | C5: % of AOP
A6: Infrastructure | B6: =SUMIF('AOP Bifurcation'!$A$2:$A$49,A6,'AOP Bifurcation'!$F$2:$F$49) | C6: =B6/$B$2
A7: Technology | B7: =SUMIF('AOP Bifurcation'!$A$2:$A$49,A7,'AOP Bifurcation'!$F$2:$F$49) | C7: =B7/$B$2
A8: Post-emergency care | B8: =SUMIF('AOP Bifurcation'!$A$2:$A$49,A8,'AOP Bifurcation'!$F$2:$F$49) | C8: =B8/$B$2
A9: Policy | B9: =SUMIF('AOP Bifurcation'!$A$2:$A$49,A9,'AOP Bifurcation'!$F$2:$F$49) | C9: =B9/$B$2
A10: Education | B10: =SUMIF('AOP Bifurcation'!$A$2:$A$49,A10,'AOP Bifurcation'!$F$2:$F$49) | C10: =B10/$B$2
A11: Trust Admin | B11: =SUMIF('AOP Bifurcation'!$A$2:$A$49,A11,'AOP Bifurcation'!$F$2:$F$49) | C11: =B11/$B$2
A12: Enabler | B12: =SUMIF('AOP Bifurcation'!$A$2:$A$49,A12,'AOP Bifurcation'!$F$2:$F$49) | C12: =B12/$B$2
A13: Contingency | B13: =SUMIF('AOP Bifurcation'!$A$2:$A$49,A13,'AOP Bifurcation'!$F$2:$F$49) | C13: =B13/$B$2
A14: Total | B14: =SUM(B6:B13)
A16: By Category (core focus area)
A17: Category (focus area) | B17: Budget (₹) | C17: % of AOP
A18: Project Rakshak | B18: =SUMIF('AOP Bifurcation'!$B$2:$B$49,A18,'AOP Bifurcation'!$F$2:$F$49) | C18: =B18/$B$2
A19: Hit & Run Compensation | B19: =SUMIF('AOP Bifurcation'!$B$2:$B$49,A19,'AOP Bifurcation'!$F$2:$F$49) | C19: =B19/$B$2
A20: Civic & GovTech (SATARK) | B20: =SUMIF('AOP Bifurcation'!$B$2:$B$49,A20,'AOP Bifurcation'!$F$2:$F$49) | C20: =B20/$B$2
A21: Marketing Campaign | B21: =SUMIF('AOP Bifurcation'!$B$2:$B$49,A21,'AOP Bifurcation'!$F$2:$F$49) | C21: =B21/$B$2
A22: Bets — School Safety Index | B22: =SUMIF('AOP Bifurcation'!$B$2:$B$49,A22,'AOP Bifurcation'!$F$2:$F$49) | C22: =B22/$B$2
A23: Bets — Gig Rider | B23: =SUMIF('AOP Bifurcation'!$B$2:$B$49,A23,'AOP Bifurcation'!$F$2:$F$49) | C23: =B23/$B$2
A24: Org Backbone | B24: =SUMIF('AOP Bifurcation'!$B$2:$B$49,A24,'AOP Bifurcation'!$F$2:$F$49) | C24: =B24/$B$2
A25: Contingency | B25: =SUMIF('AOP Bifurcation'!$B$2:$B$49,A25,'AOP Bifurcation'!$F$2:$F$49) | C25: =B25/$B$2
A26: Total | B26: =SUM(B18:B25)

Sheet Read me
A1: CFI · AOP 2026–27 — budget bifurcation (flat, pivot-ready · 4-level)
A3: COLUMNS
A4: A Vertical (functional) · B Category (focus area / programme) · C Cost group (high-level bifurcation) ·
A5: D Further bifurcation (line item) · E Description · F Budget allocated · G Remarks for Keshav.
A6: Every value repeats down the rows (no merged cells) so you can pivot at any of the four levels.
A8: HOW TO PIVOT
A9: Select 'AOP Bifurcation' ▸ Insert ▸ PivotTable. Rows: any of Vertical / Category / Cost group / line item; Values: Sum of Budget.
A10: 'Summary' reconciles to ₹6.00 Cr with a by-Vertical and a by-Category view.
A12: BASIS
A13: EXACT (board-approved AOP): Category totals — Rakshak ₹1.85 Cr, Hit & Run ₹0.60, SATARK ₹1.00, Campaign ₹0.60,
A14: Bets ₹0.20, Org Backbone ₹1.51, Contingency ₹0.24 = ₹6.00 Cr; plus Trust Admin's five headers.
A15: FIRST-PASS (edit freely): cost-group & line-item splits inside programmes, the ₹42L core vs ₹36L SMIF split,
... A22: Sources: finalized AOP deck (₹6.00 Cr) · Team Charter / Ownership Map · Slack · Gmail (Anthropic receipts, SMIF, Codex).
